qolhelpers/__init__.py
qolhelpers/geo.py
qolhelpers/images.py
qolhelpers/utils.py
qol_helpers-0.0.5.dist-info/LICENSE
qol_helpers-0.0.5.dist-info/METADATA
qol_helpers-0.0.5.dist-info/WHEEL
qol_helpers-0.0.5.dist-info/top_level.txt
qol_helpers-0.0.5.dist-info/RECORD
