Metadata-Version: 2.1
Name: qol-helpers
Version: 0.0.5
Summary: A package that offers quality of life helpers.
Author-email: Fletcher F Thompson <fletcherthompsonx@gmail.com>
License: This is free and unencumbered software released into the public domain.
Project-URL: Homepage, https://github.com/FletcherFT/qol-helpers/
Keywords: utils,helpers,quality of life
Classifier: Programming Language :: Python :: 3
Classifier: License :: OSI Approved :: MIT License
Classifier: Operating System :: OS Independent
License-File: LICENSE
Requires-Dist: tqdm
Requires-Dist: opencv-contrib-python
Requires-Dist: pillow
Requires-Dist: scikit-learn
Requires-Dist: scikit-image
